itch/reports.py
itch/log.py
itch/__init__.py
itch/times.py
itch/models.py
cli/__init__.py
cache/filetree.py
cache/rcache.py
cache/__init__.py
cache/mcache.py
reports/__init__.py
plot/__init__.py
itch-0.3.0.dist-info/WHEEL
itch-0.3.0.dist-info/RECORD
itch-0.3.0.dist-info/metadata.json
itch-0.3.0.dist-info/DESCRIPTION.rst
itch-0.3.0.dist-info/top_level.txt
itch-0.3.0.dist-info/METADATA
itch-0.3.0.dist-info/entry_points.txt
