Metadata-Version: 2.0
Name: itch
Version: 0.3.0
Summary: Twitch APIs client
Home-page: https://github.com/bibby/itch
Author: bibby
Author-email: bibby@bbby.org
License: UNKNOWN
Keywords: twitch
Platform: UNKNOWN
Requires-Dist: requests
Requires-Dist: dateutils
Requires-Dist: argparse
Provides-Extra: cache
Requires-Dist: redis; extra == 'cache'
Requires-Dist: python-memcached; extra == 'cache'
Provides-Extra: complete
Requires-Dist: python-memcached; extra == 'complete'
Requires-Dist: scipy; extra == 'complete'
Requires-Dist: redis; extra == 'complete'
Requires-Dist: matplotlib; extra == 'complete'
Provides-Extra: plot
Requires-Dist: matplotlib; extra == 'plot'
Requires-Dist: scipy; extra == 'plot'
